{
  "version": "1.0",
  "characters": [
    {
      "id": "petrel_kormorant",
      "name": "Petrel Kormorant",
      "title": "Ruler of Valaris",
      "location": "Valaris",
      "status": "alive",
      "relationship": "friendly"
    },
    {
      "id": "asdf",
      "name": "asdf",
      "title": "asd",
      "location": "",
      "description": "",
      "image": "",
      "status": "alive",
      "faction": "",
      "relationship": "ally",
      "firstMet": "",
      "notes": "",
      "createdAt": "2025-08-18T11:37:31.663Z",
      "updatedAt": "2025-08-18T11:37:31.663Z"
    }
  ],
  "lastUpdated": "2025-08-18T11:37:31.663Z"
}